dseconnectiontester/__init__.py
DSE_Software_Connection_Tester-0.0.2.dist-info/LICENSE
DSE_Software_Connection_Tester-0.0.2.dist-info/METADATA
DSE_Software_Connection_Tester-0.0.2.dist-info/WHEEL
DSE_Software_Connection_Tester-0.0.2.dist-info/top_level.txt
DSE_Software_Connection_Tester-0.0.2.dist-info/RECORD
